{
  "B2_1": ["ABI SALEH - Adrian"],
  "B3_1": ["ALLAZ - Adam", "TRICHET - Clement", "MARCHI MEKARI - Gabriel"],
  "B1_1": ["ARMBRUSTER - Alexandre", "MARIAT - Quentin"],
  "B4_2": ["ASRI Hazim", "CATHERINE - Noam"],
  "B3_2": ["AUBUT - Antoine", "DELNESTE - Etienne"],
  "B2_2": ["AVORNICITA - Madalina-nicolina", "QUEMENER - Marine"],
  "B3_3": ["BAKHAT - Ghita", "BERTRAND - Manon"],
  "B4_3": ["BARATOVA - Malika", "BRUNET - Armand"],
  "B2_3": ["BEN BOUZID - Selim", "PERRIGAULT - Simon"],
  "B3_4": ["BONKOUNGOU - Mathis", "MUHULET - Mathias"],
  "B3_5": ["BONNAMOUR - Pierre", "ROCHE - Aubin"],
  "B4_4": ["BOUSSATOU BIKAKI Friendrich amine", "CUBAUD - Mathieu"],
  "B1_2": ["BOUZIANE - Abderrahmane", "DRAVET - Eleonore"],
  "B2_4": ["BROSSAT - Pierrick", "GORISSE - Thomas"],
  "B1_3": ["CAVAGNA - Justine", "THABET - Yasmine"],
  "B4_5": ["CHAHINE - Maroun", "SAAD - Peter"],
  "B1_4": ["CHAOUKI - Youssef", "DALAOUI - Riad"],
  "B2_5": ["CHAPARD - Clement", "SCHLEE - Adam"],
  "B3_6": ["CHARLOTTE - Mateo", "DOAN - Adrien", "HUE - Simon"],
  "B4_6": ["CHAVOT - Thomas", "DIEMUNSCH - Polo"],
  "B1_5": ["CHIKHI - Djalil", "HANADER - Rayan"],
  "B2_6": ["CLOUSCARD - Theo", "MOUREAU - Alexandre"],
  "B4_7": ["COCHET - Melisse", "RJIMATI - Zineb"],
  "B3_7": ["DAI - Qinshu", "NOUR ELLIL - Hafsa"],
  "B4_10": ["DOS ANJOS GUIMARAES - Bernardo", "SAGUES RIVERA - Rafael"],
  "B1_6": ["DUGAST - Eleonore", "NAIBO - Morgane"],
  "B4_8": ["EL GHISSASSI - Saad", "GUEYE - Anta"],
  "B2_7": ["ERABHAOUI - Youssef", "SALY ABOUBAKAR"],
  "B2_8": ["ES-SOUFI - Doha", "NGO - Truong son"],
  "B1_7": ["FAKRONI - Mohamed", "LAATAR - Youssef"],
  "B3_8": ["FELZINES - Joris", "MANTZARIDES - Guillaume"],
  "B1_8": ["FOFANAS-Mariama", "ZHANG - Lizhi"],
  "B3_0": ["FOISSEY - Isaline"],
  "B4_9": ["GETENET - Mathis", "PITARD-BOUET - Aodren"],
  "B1_9": ["GOBIN - Alexis", "HOUDOUX - Adrien"],
  "B2_9": ["GOUINEAUD - Romane", "SAMAIN - Luc"],
  "B3_9": ["GRIGUER - Mehdi", "SANCHEZ - Lucas"],
  "B4_11": ["HABBA - Jassir", "PERRET - Simon"],
  "B2_10": ["HABIB - Danial", "LEVRARD - Thomas"],
  "B3_10": ["HUYNH - Huu thanh tu", "VU - Thi tho"],
  "B4_12": ["JEANNE - Corentin", "PIERRE - Juliette"],
  "B1_10": ["JOURDA - Florian", "PIGNY - Louis"],
  "B2_11": ["JOUSSOT- DUBIEN - Gabin", "ROUBAUD - Charline"],
  "B3_11": ["KUSNO - Louis", "SUN - Jixiang"],
  "B4_1": ["LARRAZ MARTIN - Diego", "SOW - Amadou"],
  "B1_11": ["LAVALLEE - Martin", "SAUCE - Marc"],
  "B2_12": ["LE VASSEUR - Florian", "MAHJOUB - Lina"],
  "B3_12": ["LOUVET DE MONTELLA - Samuel", "TAIDER - Sami"],
  "B1_12": ["MARTIN - Harold", "STEPHAN - Justine"],
  "B1_13": ["MONLUC - Constance", "SOULET - Audrey"],
  "B2_13": ["MOREAU - Karel", "SIMON - William"],
  "B3_13": ["NGUEPIE NONO - Menphis jouves", "NOUKAM - Junior"],
  "B4_13": ["SAADALLA - Nadine", "VARJABEDIAN - Noemie"],
  "B4_14": ["VENAILLE - Arno", "WILLEM - Amaury"],
  "B1_14": ["VIALLETON - Remi", "WIRANE - Hamza"]
}
